searchlogit/__init__.py
searchlogit/_choice_model.py
searchlogit/_device.py
searchlogit/akshay_test.py
searchlogit/boxcox_functions.py
searchlogit/draws.py
searchlogit/harmony.py
searchlogit/latent_class_constrained.py
searchlogit/latent_class_mixed_model.py
searchlogit/latent_class_model.py
searchlogit/latent_main.py
searchlogit/main.py
searchlogit/main_ol.py
searchlogit/misc.py
searchlogit/mixed_logit.py
searchlogit/multinomial_logit.py
searchlogit/ordered_logit.py
searchlogit/ordered_logit_mixed.py
searchlogit/ordered_logit_multinomial.py
searchlogit/r_ordered.py
searchlogit/rrm.py
searchlogit/search.py
searchlogit/siman.py
searchlogit/threshold.py
searchlogit-0.3.159.dist-info/licenses/LICENSE
searchlogit-0.3.159.dist-info/METADATA
searchlogit-0.3.159.dist-info/WHEEL
searchlogit-0.3.159.dist-info/top_level.txt
searchlogit-0.3.159.dist-info/RECORD
