Metadata-Version: 2.4
Name: searchlogit
Version: 0.3.159
Summary: Extensions for a Python package for                               GPU-accelerated estimation of mixed logit models.
Home-page: https://github.com/RyanJafefKelly/searchlogit
Author: Ryan Kelly, Prithvi Beeramoole, Zeke Ahern, Alban Pinz, Robert Burdett and Alexander Paz
Author-email: pritvi.beeramole@qut.edu.au, z.ahern@qut.edu.au
License: MIT
Requires-Python: >=3.5
License-File: LICENSE
Requires-Dist: numpy>=1.13.1
Requires-Dist: scipy>=1.0.0
Dynamic: author
Dynamic: author-email
Dynamic: description
Dynamic: description-content-type
Dynamic: home-page
Dynamic: license
Dynamic: license-file
Dynamic: requires-dist
Dynamic: requires-python
Dynamic: summary
